odoo/addons/sale_stock_warehouse_multicompany/README.rst
odoo/addons/sale_stock_warehouse_multicompany/__init__.py
odoo/addons/sale_stock_warehouse_multicompany/__manifest__.py
odoo/addons/sale_stock_warehouse_multicompany/i18n/it.po
odoo/addons/sale_stock_warehouse_multicompany/i18n/sale_stock_warehouse_multicompany.pot
odoo/addons/sale_stock_warehouse_multicompany/models/__init__.py
odoo/addons/sale_stock_warehouse_multicompany/models/sale_order.py
odoo/addons/sale_stock_warehouse_multicompany/models/sale_order_line.py
odoo/addons/sale_stock_warehouse_multicompany/models/stock_route.py
odoo/addons/sale_stock_warehouse_multicompany/models/stock_warehouse.py
odoo/addons/sale_stock_warehouse_multicompany/readme/CONFIGURE.rst
odoo/addons/sale_stock_warehouse_multicompany/readme/CONTRIBUTORS.rst
odoo/addons/sale_stock_warehouse_multicompany/readme/DESCRIPTION.rst
odoo/addons/sale_stock_warehouse_multicompany/static/description/icon.png
odoo/addons/sale_stock_warehouse_multicompany/static/description/index.html
odoo/addons/sale_stock_warehouse_multicompany/tests/__init__.py
odoo/addons/sale_stock_warehouse_multicompany/tests/test_sale_stock_warehouse_multicompany.py
odoo/addons/sale_stock_warehouse_multicompany/views/stock_route_views.xml
odoo/addons/sale_stock_warehouse_multicompany/views/stock_warehouse_views.xml
odoo_addon_sale_stock_warehouse_multicompany-16.0.1.0.0.4.dist-info/METADATA
odoo_addon_sale_stock_warehouse_multicompany-16.0.1.0.0.4.dist-info/WHEEL
odoo_addon_sale_stock_warehouse_multicompany-16.0.1.0.0.4.dist-info/top_level.txt
odoo_addon_sale_stock_warehouse_multicompany-16.0.1.0.0.4.dist-info/RECORD
