Metadata-Version: 2.1
Name: odoo-addon-sale-stock-warehouse-multicompany
Version: 16.0.1.0.0.4
Summary: Allow multiple companies to sell the stock of a shared warehouse
Home-page: https://github.com/OCA/multi-company
Author: Camptocamp, BCIM, Odoo Community Association (OCA)
Author-email: support@odoo-community.org
License: AGPL-3
Platform: UNKNOWN
Classifier: Programming Language :: Python
Classifier: Framework :: Odoo
Classifier: Framework :: Odoo :: 16.0
Classifier: License :: OSI Approved :: GNU Affero General Public License v3
Classifier: Development Status :: 3 - Alpha
Requires-Python: >=3.10
Requires-Dist: odoo <16.1dev,>=16.0a
